setup.py
KS_VM_AB_Test/Binomialdistribution.py
KS_VM_AB_Test/Experiment.py
KS_VM_AB_Test/Gaussiandistribution.py
KS_VM_AB_Test/Generaldistribution.py
KS_VM_AB_Test/__init__.py
KS_VM_AB_Test.egg-info/PKG-INFO
KS_VM_AB_Test.egg-info/SOURCES.txt
KS_VM_AB_Test.egg-info/dependency_links.txt
KS_VM_AB_Test.egg-info/not-zip-safe
KS_VM_AB_Test.egg-info/top_level.txt