Metadata-Version: 1.0
Name: KS-VM-AB-Test
Version: 0.2
Summary: AB-Testing for Advertising
Home-page: UNKNOWN
Author: Kevin Synnott
Author-email: kevinsynnott94@gmail.com
License: UNKNOWN
Platform: UNKNOWN
